README.md
setup.py
tfl/__init__.py
tfl/api_token.py
tfl/client.py
tfl/config.py
tfl/rest_client.py
tfl/models/__init__.py
tfl/models/additional_properties.py
tfl/models/affected_route.py
tfl/models/api_error.py
tfl/models/crowding.py
tfl/models/disruption.py
tfl/models/line.py
tfl/models/line_group.py
tfl/models/line_mode_group.py
tfl/models/line_status.py
tfl/models/mode.py
tfl/models/passenger_flow.py
tfl/models/prediction.py
tfl/models/prediction_timing.py
tfl/models/route_section.py
tfl/models/route_section_naptan_entry_sequence.py
tfl/models/service_type.py
tfl/models/stop_point.py
tfl/models/stop_points_response.py
tfl/models/train_loading.py
tfl/models/validity_period.py
tflunifiedapi.egg-info/PKG-INFO
tflunifiedapi.egg-info/SOURCES.txt
tflunifiedapi.egg-info/dependency_links.txt
tflunifiedapi.egg-info/not-zip-safe
tflunifiedapi.egg-info/requires.txt
tflunifiedapi.egg-info/top_level.txt