Metadata-Version: 2.1
Name: tflunifiedapi
Version: 0.2.1
Summary: Python wrapper for Transport for London (TfL) Unified API
Home-page: https://github.com/dhilmathy/TfL-python-api
Author: Mathivanan Palanisamy
Author-email: mathy@outlook.com
License: MIT
Platform: UNKNOWN
Classifier: Programming Language :: Python :: 3
Classifier: License :: OSI Approved :: MIT License
Classifier: Operating System :: OS Independent
